ACJudge_Pkg/Client.py
ACJudge_Pkg/JudgeInterface_ice.py
ACJudge_Pkg/__init__.py
ACJudge_Pkg/OJMod/__init__.py
Asymptotic_Complexity_Judge-0.0.1.dist-info/METADATA
Asymptotic_Complexity_Judge-0.0.1.dist-info/WHEEL
Asymptotic_Complexity_Judge-0.0.1.dist-info/entry_points.txt
Asymptotic_Complexity_Judge-0.0.1.dist-info/top_level.txt
Asymptotic_Complexity_Judge-0.0.1.dist-info/RECORD
