Metadata-Version: 2.1
Name: Asymptotic-Complexity-Judge
Version: 0.0.1
Summary: Terminal Judge for Asymptotic Complexity
Home-page: UNKNOWN
Author: Ehud Adler
Author-email: adlerehud@gmail.com
License: UNKNOWN
Platform: UNKNOWN
Classifier: Programming Language :: Python :: 3
Classifier: License :: OSI Approved :: MIT License
Classifier: Operating System :: OS Independent
Requires-Python: >=3.5
Requires-Dist: prettytable (>=0.7.2)
Requires-Dist: python-dotenv (>=0.12)
Requires-Dist: xtermcolor (>=1.3)
Requires-Dist: zeroc-ice (>=3.7.3)
